{"url":"https://api.github.com/repos/mowarowsea/Chotgor/issues/13","repository_url":"https://api.github.com/repos/mowarowsea/Chotgor","labels_url":"https://api.github.com/repos/mowarowsea/Chotgor/issues/13/labels{/name}","comments_url":"https://api.github.com/repos/mowarowsea/Chotgor/issues/13/comments","events_url":"https://api.github.com/repos/mowarowsea/Chotgor/issues/13/events","html_url":"https://github.com/mowarowsea/Chotgor/issues/13","id":4020349064,"node_id":"I_kwDORcjKj87voaiI","number":13,"title":"システムプロンプト改善（Chotgorの立ち位置連携、日時連携）","user":{"login":"mowarowsea","id":128439655,"node_id":"U_kgDOB6fVZw","avatar_url":"https://avatars.githubusercontent.com/u/128439655?v=4","gravatar_id":"","url":"https://api.github.com/users/mowarowsea","html_url":"https://github.com/mowarowsea","followers_url":"https://api.github.com/users/mowarowsea/followers","following_url":"https://api.github.com/users/mowarowsea/following{/other_user}","gists_url":"https://api.github.com/users/mowarowsea/gists{/gist_id}","starred_url":"https://api.github.com/users/mowarowsea/starred{/owner}{/repo}","subscriptions_url":"https://api.github.com/users/mowarowsea/subscriptions","organizations_url":"https://api.github.com/users/mowarowsea/orgs","repos_url":"https://api.github.com/users/mowarowsea/repos","events_url":"https://api.github.com/users/mowarowsea/events{/privacy}","received_events_url":"https://api.github.com/users/mowarowsea/received_events","type":"User","user_view_type":"public","site_admin":false},"labels":[],"state":"open","locked":false,"assignees":[],"milestone":null,"comments":0,"created_at":"2026-03-04T06:26:30Z","updated_at":"2026-03-04T06:26:30Z","closed_at":null,"assignee":null,"author_association":"OWNER","active_lock_reason":null,"sub_issues_summary":{"total":0,"completed":0,"percent_completed":0},"issue_dependencies_summary":{"blocked_by":0,"total_blocked_by":0,"blocking":0,"total_blocking":0},"body":"モデルへのリクエストにシステムプロンプトとして以下を含める\n- Chogorの立ち位置\n  - 「あなたはChotgorという外部ツールを使って、過去の記憶を検索できる立場です」的な。よりChotgorの哲学に沿った物言いで連携する必要はある。\n- 日時の連携\n  - これは現在の日時連携と、In-Context履歴、RAG検索結果も日時を連携する。これによって、キャラクター側が以下を検知可能になる。\n    - 今の時刻\n    - 前のメッセージからどれくらい時間が開いているのか\n    - この記憶がいつの記憶なのか\n  - この機能はオプション扱い。Chotgorの設定画面からON/OFFを切り替えられるように。","closed_by":null,"reactions":{"url":"https://api.github.com/repos/mowarowsea/Chotgor/issues/13/reactions","total_count":0,"+1":0,"-1":0,"laugh":0,"hooray":0,"confused":0,"heart":0,"rocket":0,"eyes":0},"timeline_url":"https://api.github.com/repos/mowarowsea/Chotgor/issues/13/timeline","performed_via_github_app":null,"state_reason":null,"pinned_comment":null}